exondb/__about__.py
exondb/__init__.py
exondb/cli.py
exondb/main.py
exondb-0.3.9.dist-info/METADATA
exondb-0.3.9.dist-info/WHEEL
exondb-0.3.9.dist-info/entry_points.txt
exondb-0.3.9.dist-info/licenses/LICENSE.txt
exondb-0.3.9.dist-info/RECORD
